Metadata-Version: 2.4
Name: hugging-mapper
Version: 1.0.1
Summary: A lightweight python tool for effortless text similarity scoring using Hugging Face models
Author-email: "Angel L. P." <59593766+angelphanth@users.noreply.github.com>
Project-URL: Bug Tracker, https://github.com/angelphanth/hugger/issues
Project-URL: Homepage, https://github.com/angelphanth/hugger
Classifier: Programming Language :: Python :: 3.9
Classifier: Programming Language :: Python :: 3.10
Classifier: Programming Language :: Python :: 3.11
Classifier: Programming Language :: Python :: 3.12
Classifier: License :: OSI Approved :: MIT License
Classifier: Operating System :: OS Independent
Requires-Python: >=3.9
License-File: LICENSE
Requires-Dist: appnope>=0.1.4
Requires-Dist: asttokens>=3.0.0
Requires-Dist: certifi>=2022.12.7
Requires-Dist: charset-normalizer>=3.0.0
Requires-Dist: comm>=0.2.2
Requires-Dist: debugpy>=1.8.0
Requires-Dist: decorator>=5.2.0
Requires-Dist: executing>=2.0.0
Requires-Dist: filelock>=3.8.0
Requires-Dist: fsspec>=2023.10.0
Requires-Dist: hf-xet>=1.1.5
Requires-Dist: huggingface-hub>=0.13.0
Requires-Dist: idna>=3.0
Requires-Dist: ipython<9.0,>=8.0
Requires-Dist: ipython_pygments_lexers>=1.1.1
Requires-Dist: jedi>=0.19.0
Requires-Dist: Jinja2>=3.0.0
Requires-Dist: joblib>=1.2.0
Requires-Dist: jupyter_client>=8.0.0
Requires-Dist: jupyter_core>=5.0.0
Requires-Dist: MarkupSafe>=2.0.0
Requires-Dist: matplotlib-inline>=0.1.6
Requires-Dist: mpmath>=1.2.0
Requires-Dist: nest-asyncio>=1.5.0
Requires-Dist: networkx>=3.0
Requires-Dist: numpy>=1.21.0
Requires-Dist: packaging>=21.0
Requires-Dist: pandas>=1.3.0
Requires-Dist: parso>=0.8.0
Requires-Dist: pexpect>=4.8.0
Requires-Dist: platformdirs>=3.0.0
Requires-Dist: prompt_toolkit>=3.0.0
Requires-Dist: psutil>=5.9.0
Requires-Dist: ptyprocess>=0.7.0
Requires-Dist: pure_eval>=0.2.0
Requires-Dist: Pygments>=2.10.0
Requires-Dist: python-dateutil>=2.8.0
Requires-Dist: pytz>=2022.0
Requires-Dist: PyYAML>=6.0.0
Requires-Dist: pyzmq>=25.0.0
Requires-Dist: regex>=2023.0.0
Requires-Dist: requests>=2.28.0
Requires-Dist: safetensors>=0.3.0
Requires-Dist: scikit-learn>=1.1.0
Requires-Dist: scipy>=1.7.0
Requires-Dist: six>=1.16.0
Requires-Dist: stack-data>=0.6.0
Requires-Dist: sympy>=1.10.0
Requires-Dist: threadpoolctl>=3.1.0
Requires-Dist: tokenizers>=0.13.0
Requires-Dist: torch>=1.12.0
Requires-Dist: tornado>=6.2.0
Requires-Dist: tqdm>=4.64.0
Requires-Dist: traitlets>=5.3.0
Requires-Dist: transformers>=4.26.0
Requires-Dist: typing_extensions>=4.0.0
Requires-Dist: tzdata>=2022.0
Requires-Dist: urllib3>=1.26.0
Requires-Dist: wcwidth>=0.2.5
Provides-Extra: docs
Requires-Dist: sphinx; extra == "docs"
Requires-Dist: sphinx-book-theme; extra == "docs"
Requires-Dist: myst-nb; extra == "docs"
Requires-Dist: ipywidgets; extra == "docs"
Requires-Dist: sphinx-new-tab-link!=0.2.2; extra == "docs"
Requires-Dist: jupytext; extra == "docs"
Provides-Extra: dev
Requires-Dist: black; extra == "dev"
Requires-Dist: ruff; extra == "dev"
Requires-Dist: pytest; extra == "dev"
Requires-Dist: ipykernel; extra == "dev"
Requires-Dist: openpyxl; extra == "dev"
Dynamic: license-file
